jira_easy/__init__.py
jira_easy/client.py
jira_easy-1.0.2.dist-info/LICENSE
jira_easy-1.0.2.dist-info/METADATA
jira_easy-1.0.2.dist-info/WHEEL
jira_easy-1.0.2.dist-info/top_level.txt
jira_easy-1.0.2.dist-info/RECORD
