Metadata-Version: 2.2
Name: jira_easy
Version: 1.0.2
Summary: A simple Python library for fetching JIRA issues using JQL.
Home-page: https://github.com/ahgq7/jira_easy
Author: Abdulhamit Güngören
Author-email: abdulhamitgungoren@gmail.com
Classifier: Programming Language :: Python :: 3
Classifier: License :: OSI Approved :: MIT License
Classifier: Operating System :: OS Independent
Requires-Python: >=3.6
License-File: LICENSE
Requires-Dist: requests>=2.25.1
Dynamic: author
Dynamic: author-email
Dynamic: classifier
Dynamic: description
Dynamic: description-content-type
Dynamic: home-page
Dynamic: requires-dist
Dynamic: requires-python
Dynamic: summary
